[
  {
    "id": 7,
    "products": [
      {
        "id": 3,
        "quantity": 10
      },
      {
        "id": 2,
        "quantity": 20
      }
    ]
  },
  {
    "id": 6,
    "products": [
      {
        "id": 3,
        "quantity": 10
      },
      {
        "id": 2,
        "quantity": 23
      },
      {
        "id": 4,
        "quantity": 3
      },
      {
        "id": 6,
        "quantity": 1
      }
    ]
  },
  {
    "id": 8,
    "products": [
      {
        "id": 2,
        "quantity": 1
      },
      {
        "id": 6,
        "quantity": 2
      },
      {
        "id": 9,
        "quantity": 1
      }
    ]
  },
  {
    "id": 10,
    "products": [
      {
        "id": 2,
        "quantity": 1
      }
    ]
  },
  {
    "id": 11,
    "products": [
      {
        "id": 2,
        "quantity": 1
      }
    ]
  },
  {
    "id": 12,
    "products": [
      {
        "id": 2,
        "quantity": 1
      }
    ]
  },
  {
    "id": 13,
    "products": [
      {
        "id": 2,
        "quantity": 1
      }
    ]
  },
  {
    "id": 14,
    "products": [
      {
        "id": 2,
        "quantity": 1
      }
    ]
  },
  {
    "id": 15,
    "products": [
      {
        "id": 2,
        "quantity": 1
      }
    ]
  },
  {
    "id": 9,
    "products": [
      {
        "id": 2,
        "quantity": 1
      },
      {
        "id": 9,
        "quantity": 2041
      }
    ]
  },
  {
    "id": 16,
    "products": []
  },
  {
    "id": 17,
    "products": []
  },
  {
    "id": 18,
    "products": []
  },
  {
    "id": 19,
    "products": []
  },
  {
    "id": 20,
    "products": [
      {
        "id": 9,
        "quantity": 3
      },
      {
        "id": 4,
        "quantity": 1
      }
    ]
  }
]